emberblast/__init__.py
emberblast/__main__.py
emberblast/bot/__init__.py
emberblast/bot/bot_decisioning.py
emberblast/communicator/__init__.py
emberblast/communicator/communicator.py
emberblast/communicator/communicator_cmd.py
emberblast/communicator/informer_cmd.py
emberblast/communicator/level_up.py
emberblast/communicator/questioner_cmd.py
emberblast/conf/__init__.py
emberblast/conf/conf.py
emberblast/conf/conf.yaml
emberblast/conf/items.yaml
emberblast/conf/logger.py
emberblast/conf/schema.py
emberblast/conf/side_effects.yaml
emberblast/conf/skills.yaml
emberblast/effect/__init__.py
emberblast/effect/side_effects.py
emberblast/exception/__init__.py
emberblast/exception/exception.py
emberblast/game/__init__.py
emberblast/game/game.py
emberblast/game/game_factory.py
emberblast/img/emberblast.png
emberblast/interface/__init__.py
emberblast/interface/interface.py
emberblast/item/__init__.py
emberblast/item/bag.py
emberblast/item/equipment.py
emberblast/item/items.py
emberblast/map/__init__.py
emberblast/map/graph.py
emberblast/map/map.py
emberblast/orchestrator/__init__.py
emberblast/orchestrator/game_orchestrator.py
emberblast/player/__init__.py
emberblast/player/bot_player.py
emberblast/player/controlled_player.py
emberblast/player/job.py
emberblast/player/player.py
emberblast/player/race.py
emberblast/save/__init__.py
emberblast/save/save.py
emberblast/saved_games/__init__.py
emberblast/skill/__init__.py
emberblast/skill/skill.py
emberblast/test/__init__.py
emberblast/test/test.py
emberblast/test/test_bot_decisioning.py
emberblast/test/test_conf.py
emberblast/test/test_game.py
emberblast/test/test_item.py
emberblast/test/test_map.py
emberblast/test/test_message.py
emberblast/test/test_player.py
emberblast/test/test_questions_cmd.py
emberblast/test/test_skill.py
emberblast/test/test_utils.py
emberblast/utils/__init__.py
emberblast/utils/constants.py
emberblast/utils/utils.py
emberblast/utils/name_generator/__init__.py
Emberblast-1.0.7.dist-info/LICENSE
Emberblast-1.0.7.dist-info/METADATA
Emberblast-1.0.7.dist-info/WHEEL
Emberblast-1.0.7.dist-info/entry_points.txt
Emberblast-1.0.7.dist-info/top_level.txt
Emberblast-1.0.7.dist-info/RECORD
