Metadata-Version: 2.1
Name: Emberblast
Version: 1.0.7
Summary: Medieval Turn based RPG
Home-page: https://github.com/felipemeriga/Emberblast
Author: Felipe Meriga
Author-email: felipe.meriga@gmail.com
License: UNKNOWN
Project-URL: Bug Tracker, https://github.com/felipemeriga/Emberblast/issues
Platform: UNKNOWN
Classifier: Programming Language :: Python :: 3.8
Classifier: Programming Language :: Python :: 3.9
Classifier: Programming Language :: Python :: 3.10
Classifier: License :: OSI Approved :: MIT License
Classifier: Operating System :: OS Independent
Requires-Python: >=3.8
License-File: LICENSE
Requires-Dist: timg (>=1.1.5)
Requires-Dist: InquirerPy (>=0.2.0)
Requires-Dist: colorama (>=0.4.4)
Requires-Dist: PyYAML (>=5.4.1)
Requires-Dist: Cerberus (>=1.3.4)
Requires-Dist: emojis (>=0.6.0)
Requires-Dist: numpy (>=1.21.1)
Requires-Dist: sqlparse (>=0.4.1)
Requires-Dist: termcolor (>=1.1.0)
Requires-Dist: cloudpickle (>=1.6.0)
